adafilt/__init__.py
adafilt/io.py
adafilt/optimal.py
adafilt/utils.py
adafilt-0.1.0.dist-info/METADATA
adafilt-0.1.0.dist-info/WHEEL
adafilt-0.1.0.dist-info/licenses/LICENSE
adafilt-0.1.0.dist-info/RECORD
