Metadata-Version: 2.3
Name: adafilt
Version: 0.1.0
Summary: Adaptive filters for 🐍
Project-URL: repository, https://github.com/fhchl/adafilt
Author-email: "Franz M. Heuchel" <franz.heuchel@gmail.com>
License: MIT License
Keywords: adaptive-filters,dsp,signal-processing
Classifier: Intended Audience :: Science/Research
Classifier: License :: OSI Approved :: MIT License
Classifier: Programming Language :: Python :: 3
Classifier: Topic :: Multimedia :: Sound/Audio
Classifier: Topic :: Scientific/Engineering
Requires-Python: >=3.8
Requires-Dist: numpy>=1
Provides-Extra: dev
Requires-Dist: pytest; extra == 'dev'
Requires-Dist: ruff; extra == 'dev'
Requires-Dist: scipy; extra == 'dev'
